sphinx_roles/__init__.py
sphinx_roles/_version.py
sphinx_roles/domain.py
sphinx_roles/roles.py
sphinx_roles-0.1.0.dist-info/licenses/LICENSE
sphinx_roles-0.1.0.dist-info/METADATA
sphinx_roles-0.1.0.dist-info/WHEEL
sphinx_roles-0.1.0.dist-info/top_level.txt
sphinx_roles-0.1.0.dist-info/RECORD
